bandwidth_cli/__init__.py
bandwidth_cli/commands/__init__.py
bandwidth_cli/commands/create.py
bandwidth_cli/commands/delete.py
bandwidth_cli/commands/get.py
bandwidth_cli/commands/retrieve.py
bandwidth_cli/main.py
bandwidth_cli-0.1.4.dist-info/entry_points.txt
bandwidth_cli-0.1.4.dist-info/WHEEL
bandwidth_cli-0.1.4.dist-info/METADATA
bandwidth_cli-0.1.4.dist-info/RECORD
