Metadata-Version: 2.1
Name: bandwidth-cli
Version: 0.1.4
Summary: CLI for Bandwidth API calls
Author: Malaney J Hill
Author-email: mhill@phone.com
Requires-Python: >=3.7,<4.0
Classifier: Programming Language :: Python :: 3
Classifier: Programming Language :: Python :: 3.10
Classifier: Programming Language :: Python :: 3.7
Classifier: Programming Language :: Python :: 3.8
Classifier: Programming Language :: Python :: 3.9
Requires-Dist: click (>=8.0.4,<9.0.0)
Requires-Dist: python-dotenv (>=0.19.2,<0.20.0)
Requires-Dist: requests (>=2.27.1,<3.0.0)
Requires-Dist: xmltodict (>=0.12.0,<0.13.0)
